lockmgr/__init__.py
lockmgr/apps.py
lockmgr/lockmgr.py
lockmgr/models.py
lockmgr/settings.py
lockmgr/management/__init__.py
lockmgr/management/commands/__init__.py
lockmgr/management/commands/clear_lock.py
lockmgr/management/commands/list_locks.py
lockmgr/management/commands/reset_locks.py
lockmgr/management/commands/set_lock.py
lockmgr/migrations/0001_initial.py
lockmgr/migrations/0002_auto_20191121_2308.py
lockmgr/migrations/__init__.py
django_lockmgr-2.0.0.dist-info/LICENSE
django_lockmgr-2.0.0.dist-info/METADATA
django_lockmgr-2.0.0.dist-info/WHEEL
django_lockmgr-2.0.0.dist-info/top_level.txt
django_lockmgr-2.0.0.dist-info/RECORD
