Metadata-Version: 2.1
Name: django-lockmgr
Version: 2.0.0
Summary: A locking system for Django apps simply using the database.
Home-page: https://github.com/Privex/django-lockmgr
Author: Chris (Someguy123) @ Privex
Author-email: chris@privex.io
License: MIT
Platform: UNKNOWN
Classifier: Programming Language :: Python :: 3
Classifier: Programming Language :: Python :: 3.6
Classifier: Programming Language :: Python :: 3.7
Classifier: Programming Language :: Python :: 3.8
Classifier: Framework :: Django
Classifier: Framework :: Django :: 1.10
Classifier: Framework :: Django :: 1.11
Classifier: Framework :: Django :: 2.0
Classifier: Framework :: Django :: 2.1
Classifier: Framework :: Django :: 2.2
Classifier: License :: OSI Approved :: MIT License
Classifier: Operating System :: OS Independent
Requires-Dist: Django
Requires-Dist: privex-helpers (>=2.0.0)
Requires-Dist: python-dateutil
Requires-Dist: pytz
